CHANGELOG.md
case_style_changer/__init__.py
case_style_changer/case_changer.py
case_style_changer/case_guesser.py
case_style_changer/case_style.py
case_style_changer/cli.py
case_style_changer/text_splitter.py
case_style_changer-0.1.3.dist-info/entry_points.txt
case_style_changer-0.1.3.dist-info/LICENSE
case_style_changer-0.1.3.dist-info/WHEEL
case_style_changer-0.1.3.dist-info/METADATA
case_style_changer-0.1.3.dist-info/RECORD
