Metadata-Version: 2.1
Name: case-style-changer
Version: 0.1.3
Summary: Case Style Changer - a CLI tool that guesses the case of the input string and converts it to another case.
Home-page: https://github.com/xkumiyu/case-style-changer
License: MIT
Author: xkumiyu
Author-email: xkumiyu@gmail.com
Requires-Python: >=3.6
Classifier: Environment :: Console
Classifier: License :: OSI Approved :: MIT License
Classifier: Programming Language :: Python :: 3
Classifier: Programming Language :: Python :: 3.6
Classifier: Programming Language :: Python :: 3.7
Classifier: Programming Language :: Python :: 3.8
Classifier: Programming Language :: Python :: 3.9
Classifier: Topic :: Utilities
Project-URL: Repository, https://github.com/xkumiyu/case-style-changer
